lab0/src/acumulador2/acumulador2.v
`timescale 1ns / 1ps


//funciona igual que acumulador 1 lo que varia es la condicion para pasar del add al done
module acumulador2 (
    input wire clk,
    input wire rst,
    input wire start,
    input wire [3:0] x,
    output reg [5:0] acc,
    output reg done
);

    // Definición de estados
    localparam IDLE = 2'b00;
    localparam LOAD = 2'b01;
    localparam ADD  = 2'b10;
    localparam DONE = 2'b11;

    // Registro de estado
    reg [1:0] state;

    always @(posedge clk or posedge rst) begin
        if (rst) begin
            state <= IDLE;
            acc <= 6'd0;
            done <= 1'b0;
        end else begin
            case (state)
                IDLE: begin
                    done <= 1'b0; // Asegurar que done esté en 0
                    if (start) begin
                        state <= LOAD;
                    end
                end
                
                LOAD: begin
                    acc <= 6'd0;  // Inicializa el acumulador en cero
                    state <= ADD;
                end
                
                ADD: begin
                    acc <= acc + x; // Acumula el valor de x
                    
                    // Si el valor que se está guardando es mayor o igual a 20, terminamos
                    if ((acc + x) >= 6'd20) begin
                        state <= DONE;
                    end
                end
                
                DONE: begin
                    done <= 1'b1;  // Activa la señal done por un ciclo
                    state <= IDLE; // Retorna a IDLE en el siguiente ciclo
                end
                
                default: state <= IDLE;
            endcase
        end
    end

endmodule

lab0/src/acumulador2/tb_acumulador2.v
`timescale 1ns / 1ps
`include "Laboratorio-Digital-2/lab0/acumulador2.v"
module tb_acumulador2;

    // Entradas del DUT
    reg clk;
    reg rst;
    reg start;
    reg [3:0] x;

    // Salidas del DUT
    wire [5:0] acc;
    wire done;

    // Instanciación del módulo
    acumulador2 uut (
        .clk(clk),
        .rst(rst),
        .start(start),
        .x(x),
        .acc(acc),
        .done(done)
    );

    // Generación del reloj (Periodo de 10ns)
    always #5 clk = ~clk;

    initial begin
        // Generación de archivos para GTKWave
        $dumpfile("acumulador2.vcd");
        $dumpvars(0, tb_acumulador2);

        // Inicialización de señales
        clk = 0;
        rst = 1;
        start = 0;
        x = 4'd0;

        // Liberar reset después de 15ns
        #15 rst = 0;
        
        // ----------------------------------------------------
        // Prueba 1: Sumar x = 6 (Acumulará 6, 12, 18, 24)
        // ----------------------------------------------------
        #10;
        x = 4'd6;
        start = 1;
        #10 start = 0; // Pulso de inicio
        
        wait(done == 1'b1);
        $display("Prueba 1 Terminada. Resultado acc = %d (Esperado: 24)", acc);
        
        #20;

        // ----------------------------------------------------
        // Prueba 2: Sumar x = 5 (Acumulará 5, 10, 15, 20)
        // ----------------------------------------------------
        x = 4'd5;
        start = 1;
        #10 start = 0;
        
        wait(done == 1'b1);
        $display("Prueba 2 Terminada. Resultado acc = %d (Esperado: 20)", acc);
        
        #30;
        
        // Finalizar simulación
        $finish;
    end

endmodule

lab0/src/acumulador2/acumulador2.vcd
$date
	Thu Sep 10 17:34:44 2026
$end
$version
	Icarus Verilog
$end
$timescale
	1ps
$end
$scope module tb_acumulador2 $end
$var wire 1 ! done $end
$var wire 6 " acc [5:0] $end
$var reg 1 # clk $end
$var reg 1 $ rst $end
$var reg 1 % start $end
$var reg 4 & x [3:0] $end
$scope module uut $end
$var wire 1 # clk $end
$var wire 1 $ rst $end
$var wire 1 % start $end
$var wire 4 ' x [3:0] $end
$var parameter 2 ( ADD $end
$var parameter 2 ) DONE $end
$var parameter 2 * IDLE $end
$var parameter 2 + LOAD $end
$var reg 6 , acc [5:0] $end
$var reg 1 ! done $end
$var reg 2 - state [1:0] $end
$upscope $end
$upscope $end
$enddefinitions $end
$comment Show the parameter values. $end
$dumpall
b1 +
b0 *
b11 )
b10 (
$end
#0
$dumpvars
b0 -
b0 ,
b0 '
b0 &
0%
1$
0#
b0 "
0!
$end
#5000
1#
#10000
0#
#15000
1#
0$
#20000
0#
#25000
b1 -
1#
1%
b110 &
b110 '
#30000
0#
#35000
b10 -
1#
0%
#40000
0#
#45000
b110 "
b110 ,
1#
#50000
0#
#55000
b1100 "
b1100 ,
1#
#60000
0#
#65000
b10010 "
b10010 ,
1#
#70000
0#
#75000
b11 -
b11000 "
b11000 ,
1#
#80000
0#
#85000
b0 -
1!
1#
#90000
0#
#95000
0!
1#
#100000
0#
#105000
b1 -
1#
1%
b101 &
b101 '
#110000
0#
#115000
b10 -
b0 "
b0 ,
1#
0%
#120000
0#
#125000
b101 "
b101 ,
1#
#130000
0#
#135000
b1010 "
b1010 ,
1#
#140000
0#
#145000
b1111 "
b1111 ,
1#
#150000
0#
#155000
b11 -
b10100 "
b10100 ,
1#
#160000
0#
#165000
b0 -
1!
1#
#170000
0#
#175000
0!
1#
