lab1/src/Aritmetica/l_aritmetica.v

module l_aritmetica (
    input  wire [3:0] sw,
    input  wire [5:0] btn,
    // LED SUMA O RESTA
    output wire [3:0] led,
    // LED RGB
    output wire       y,
    output wire       o,
    output wire       xo
);

    wire [3:0] A     = sw;
    wire [3:0] B_raw = btn[3:0];
    wire [3:0] B = B_raw ^ {4{btn[5]}}; //invertir bits

    // operaciones lógicas
    wire [3:0] AND_result = A & B;
    wire [3:0] OR_result  = A | B;
    wire [3:0] XOR_result = A ^ B;

    wire [3:0] SUM_result = btn[4] ? (A - B) : (A + B); // se suma o se resta

    // Salidas
    assign led   = SUM_result;
    assign y = |AND_result;   // Rojo:  AND
    assign o = |OR_result;    // Verde: OR 
    assign xo = |XOR_result;   // Azul:  XOR 

endmodule

lab1/src/Aritmetica/tb_l_aritmetica.v
`timescale 1ns / 1ps
`include "l_aritmetica.v"

module tb_l_aritmetica;

    reg [3:0] sw;
    reg [5:0] btn;
    wire [3:0] led;
    wire y;
    wire o;
    wire xo;

    l_aritmetica uut (  
        .sw(sw),
        .btn(btn),
        .led(led),
        .y(y),
        .o(o),
        .xo(xo)
    );


    initial begin
        // btn = {BTN5, BTN4, B[3:0]}
 
        sw = 4'b0011; btn = 6'b00_0010; #10;  // 3 + 2 = 5
        sw = 4'b0110; btn = 6'b00_0001; #10;  // 6 + 1 = 7
        sw = 4'b0100; btn = 6'b00_0100; #10;  // 4 + 4 = 8
        sw = 4'b0111; btn = 6'b01_0010; #10;  // 7 - 2 = 5
        sw = 4'b0101; btn = 6'b01_0101; #10;  // 5 - 5 = 0
        sw = 4'b0110; btn = 6'b10_0010; #10;  // 6 + (-2) = 4
        sw = 4'b0101; btn = 6'b00_0010; #10;  // 5 + 2 = 7
        sw = 4'b1111; btn = 6'b00_0001; #10;  // 15z + 1 = 16
 
        $finish;
    end


    initial begin
        $dumpfile("tb_l_aritmetica.vcd");
        $dumpvars(0, tb_l_aritmetica);

        $monitor("Time: %0dns, SW: %b, BTN: %b, LED: %b, Y: %b, O: %b, XO: %b", 
                  $time, sw, btn, led, y, o, xo);
    end

endmodule

lab1/src/Aritmetica/tb_l_aritmetica.vcd
$date
	Thu Oct 01 21:22:02 2026
$end
$version
	Icarus Verilog
$end
$timescale
	1ps
$end
$scope module tb_l_aritmetica $end
$var wire 1 ! y $end
$var wire 1 " xo $end
$var wire 1 # o $end
$var wire 4 $ led [3:0] $end
$var reg 6 % btn [5:0] $end
$var reg 4 & sw [3:0] $end
$scope module uut $end
$var wire 4 ' A [3:0] $end
$var wire 4 ( AND_result [3:0] $end
$var wire 4 ) B [3:0] $end
$var wire 4 * OR_result [3:0] $end
$var wire 4 + XOR_result [3:0] $end
$var wire 6 , btn [5:0] $end
$var wire 4 - led [3:0] $end
$var wire 4 . sw [3:0] $end
$var wire 1 ! y $end
$var wire 1 " xo $end
$var wire 1 # o $end
$var wire 4 / SUM_result [3:0] $end
$var wire 4 0 B_raw [3:0] $end
$upscope $end
$upscope $end
$enddefinitions $end
$comment Show the parameter values. $end
$dumpall
$end
#0
$dumpvars
b10 0
b101 /
b11 .
b101 -
b10 ,
b1 +
b11 *
b10 )
b10 (
b11 '
b11 &
b10 %
b101 $
1#
1"
1!
$end
#10000
0!
b0 (
b1 )
b1 0
b111 *
b111 +
b111 $
b111 -
b111 /
b1 %
b1 ,
b110 '
b110 &
b110 .
#20000
1!
b100 (
0"
b100 )
b100 0
b100 *
b0 +
b1000 $
b1000 -
b1000 /
b100 %
b100 ,
b100 '
b100 &
b100 .
#30000
b10 (
b10 )
b10 0
b111 *
1"
b101 +
b101 $
b101 -
b101 /
b10010 %
b10010 ,
b111 '
b111 &
b111 .
#40000
b101 *
0"
b101 )
b101 0
1!
b101 (
b0 +
b0 $
b0 -
b0 /
b10101 %
b10101 ,
b101 '
b101 &
b101 .
#50000
b1101 )
b10 0
b100 (
b1111 *
1"
b1011 +
b11 $
b11 -
b11 /
b100010 %
b100010 ,
b110 '
b110 &
b110 .
#60000
0!
b10 )
b0 (
b111 *
b111 +
b111 $
b111 -
b111 /
b10 %
b10 ,
b101 '
b101 &
b101 .
#70000
b1 )
b1 0
1!
b1 (
b1111 *
b1110 +
b0 $
b0 -
b0 /
b1 %
b1 ,
b1111 '
b1111 &
b1111 .
