lab0/src/acumulador/acumulador.v
`timescale 1ns / 1ps

module acumulador (
    input wire clk,
    input wire rst,
    input wire start,
    input wire [3:0] x,
    output reg [5:0] acc,
    output reg done
);

    // Definición de estados usando localparam
    localparam IDLE = 2'b00;
    localparam LOAD = 2'b01;
    localparam ADD  = 2'b10;
    localparam DONE = 2'b11;

    // Registros internos
    reg [1:0] state;
    reg [1:0] count; // Contador para saber cuántas veces hemos sumado

    // Parámetro para la variante aca puede ser 3 o 4.
    localparam MAX_ADDS = 3; 

    always @(posedge clk or posedge rst) begin
        if (rst) begin
            state <= IDLE;
            acc <= 6'd0;
            count <= 2'd0;
            done <= 1'b0;
        end else begin
            case (state)
                IDLE: begin
                    done <= 1'b0; // Asegurar que done esté en 0
                    if (start) begin
                        state <= LOAD;
                    end
                end
                
                LOAD: begin
                    acc <= 6'd0;  // Inicializa el acumulador en cero
                    count <= 2'd0; // Reinicia el contador
                    state <= ADD;
                end
                
                ADD: begin
                    acc <= acc + x; // Acumula el valor de x
                    count <= count + 1;
                    
                    // Si ya sumamos la cantidad de veces deseada, pasamos a DONE
                    if (count == MAX_ADDS - 1) begin
                        state <= DONE;
                    end
                end
                
                DONE: begin
                    done <= 1'b1; // Activa la señal done por un ciclo
                    state <= IDLE; // Retorna a IDLE en el siguiente ciclo
                end
                
                default: state <= IDLE;
            endcase
        end
    end

endmodule

lab0/src/acumulador/tb_acumulador.v
`timescale 1ns / 1ps
`include "Laboratorio-Digital-2/lab0/acumulador.v"

module tb_acumulador;

    // Entradas del DUT (Device Under Test)
    reg clk;
    reg rst;
    reg start;
    reg [3:0] x;

    // Salidas del DUT
    wire [5:0] acc;
    wire done;

    // Instanciación del módulo
    acumulador uut (
        .clk(clk),
        .rst(rst),
        .start(start),
        .x(x),
        .acc(acc),
        .done(done)
    );

    // Generación del reloj (Periodo de 10ns)
    always #5 clk = ~clk;

    initial begin
        // Generación de archivos para GTKWave
        $dumpfile("acumulador.vcd");
        $dumpvars(0, tb_acumulador);

        // Inicialización de señales
        clk = 0;
        rst = 1;
        start = 0;
        x = 4'd0;

        // Liberar reset después de 15ns
        #15 rst = 0;
        
        // ----------------------------------------------------
        // Prueba 1: Sumar x = 5 (El resultado debe ser 15)
        // ----------------------------------------------------
        #10;
        x = 4'd5;
        start = 1;
        #10 start = 0; // start debe ser un pulso de un ciclo
        
        // Esperar a que el módulo termine (done == 1)
        wait(done == 1'b1);
        $display("Prueba 1 Terminada. Resultado acc = %d (Esperado: 15)", acc);
        
        #20; // Esperar un poco antes de la siguiente prueba

        // ----------------------------------------------------
        // Prueba 2: Sumar x = 7 (El resultado debe ser 21)
        // ----------------------------------------------------
        x = 4'd7;
        start = 1;
        #10 start = 0;
        
        wait(done == 1'b1);
        $display("Prueba 2 Terminada. Resultado acc = %d (Esperado: 21)", acc);
        
        #30;
        
        // Finalizar simulación
        $finish;
    end

endmodule

lab0/src/acumulador/acumulador.vcd
$date
	Thu Sep 10 17:27:55 2026
$end
$version
	Icarus Verilog
$end
$timescale
	1ps
$end
$scope module tb_acumulador $end
$var wire 1 ! done $end
$var wire 6 " acc [5:0] $end
$var reg 1 # clk $end
$var reg 1 $ rst $end
$var reg 1 % start $end
$var reg 4 & x [3:0] $end
$scope module uut $end
$var wire 1 # clk $end
$var wire 1 $ rst $end
$var wire 1 % start $end
$var wire 4 ' x [3:0] $end
$var parameter 2 ( ADD $end
$var parameter 2 ) DONE $end
$var parameter 2 * IDLE $end
$var parameter 2 + LOAD $end
$var parameter 32 , MAX_ADDS $end
$var reg 6 - acc [5:0] $end
$var reg 2 . count [1:0] $end
$var reg 1 ! done $end
$var reg 2 / state [1:0] $end
$upscope $end
$upscope $end
$enddefinitions $end
$comment Show the parameter values. $end
$dumpall
b11 ,
b1 +
b0 *
b11 )
b10 (
$end
#0
$dumpvars
b0 /
b0 .
b0 -
b0 '
b0 &
0%
1$
0#
b0 "
0!
$end
#5000
1#
#10000
0#
#15000
1#
0$
#20000
0#
#25000
b1 /
1#
1%
b101 &
b101 '
#30000
0#
#35000
b10 /
1#
0%
#40000
0#
#45000
b1 .
b101 "
b101 -
1#
#50000
0#
#55000
b10 .
b1010 "
b1010 -
1#
#60000
0#
#65000
b11 /
b11 .
b1111 "
b1111 -
1#
#70000
0#
#75000
b0 /
1!
1#
#80000
0#
#85000
0!
1#
#90000
0#
#95000
b1 /
1#
1%
b111 &
b111 '
#100000
0#
#105000
b10 /
b0 .
b0 "
b0 -
1#
0%
#110000
0#
#115000
b1 .
b111 "
b111 -
1#
#120000
0#
#125000
b10 .
b1110 "
b1110 -
1#
#130000
0#
#135000
b11 /
b11 .
b10101 "
b10101 -
1#
#140000
0#
#145000
b0 /
1!
1#
#150000
0#
#155000
0!
1#
