lab0/semaforo1.v
module semaforo(
    input  wire clk,
    input  wire rst,
    output reg [1:0] verde,
    output reg [1:0] amarillo,
    output reg [1:0] rojo

    
);

localparam S0 = 2'b00;
localparam S1 = 2'b01;
localparam S2 = 2'b10;
reg [3:0] contador;
reg [1:0] estado;



always @(posedge clk or posedge rst) begin
    if(rst)begin
        estado <= S0;
        contador <= 0;
    end
    else begin
        if (estado == S0)begin

            verde = 2'b01;
            amarillo = 2'b00;
            rojo = 2'b00;
            if (contador == 4) begin
                estado <= S1;
            end
                else begin
                    contador <= contador + 1;
                end
        end

        if (estado == S1)begin
            verde = 2'b00;
            amarillo = 2'b01;
            rojo = 2'b00;
            if (contador == 6) begin
                estado <= S2;
            end
            else begin
                    contador <= contador + 1;
                end
            if (contador ==  12) begin
                estado <= S0;
            end
        end
        
        if (estado == S2)begin
            verde = 2'b00;
            amarillo = 2'b00;
            rojo = 2'b01;
            if (contador == 10) begin
                estado <= S1;
            end
                else begin
                    contador <= contador + 1;
                end
        end
    end
end

endmodule

lab0/tb_semaforo.v
`timescale 1ns/1ps
`include "semaforo1.v"

module tb_semaforo;

    // Señales del testbench
    reg clk;
    reg rst;

    wire [1:0] verde;
    wire [1:0] amarillo;
    wire [1:0] rojo;

    // Instancia del módulo a probar
    semaforo uut (
        .clk(clk),
        .rst(rst),
        .verde(verde),
        .amarillo(amarillo),
        .rojo(rojo)
    );

    // Generador de reloj
    always #5 clk = ~clk;

    // Secuencia de prueba
    initial begin

        // Inicialización
        clk = 0;
        rst = 1;

        // Mantener reset durante 20 ns
        #20;
        rst = 0;

        // Dejar correr la simulación
        #200;

        // Finalizar
        $finish;
    end

    // Mostrar valores en consola
    initial begin
    // Generación del archivo de ondas
    $dumpfile("semaforo1.vcd");
    $dumpvars(0, tb_semaforo);

        $monitor("Tiempo = %0t | rst = %b | estado = %b | contador = %d | verde = %b | amarillo = %b | rojo = %b",
                 $time,
                 rst,
                 uut.estado,
                 uut.contador,
                 verde,
                 amarillo,
                 rojo);
    end

endmodule

lab0/semaforo1.vcd
$date
	Thu Sep 10 16:08:52 2026
$end
$version
	Icarus Verilog
$end
$timescale
	1ps
$end
$scope module tb_semaforo $end
$var wire 2 ! verde [1:0] $end
$var wire 2 " rojo [1:0] $end
$var wire 2 # amarillo [1:0] $end
$var reg 1 $ clk $end
$var reg 1 % rst $end
$scope module uut $end
$var wire 1 $ clk $end
$var wire 1 % rst $end
$var parameter 2 & S0 $end
$var parameter 2 ' S1 $end
$var parameter 2 ( S2 $end
$var reg 2 ) amarillo [1:0] $end
$var reg 4 * contador [3:0] $end
$var reg 2 + estado [1:0] $end
$var reg 2 , rojo [1:0] $end
$var reg 2 - verde [1:0] $end
$upscope $end
$upscope $end
$enddefinitions $end
$comment Show the parameter values. $end
$dumpall
b10 (
b1 '
b0 &
$end
#0
$dumpvars
bx -
bx ,
b0 +
b0 *
bx )
1%
0$
bx #
bx "
bx !
$end
#5000
1$
#10000
0$
#15000
1$
#20000
0$
0%
#25000
b1 *
b0 "
b0 ,
b0 #
b0 )
b1 !
b1 -
1$
#30000
0$
#35000
b10 *
1$
#40000
0$
#45000
b11 *
1$
#50000
0$
#55000
b100 *
1$
#60000
0$
#65000
b1 +
1$
#70000
0$
#75000
b101 *
b1 #
b1 )
b0 !
b0 -
1$
#80000
0$
#85000
b110 *
1$
#90000
0$
#95000
b10 +
1$
#100000
0$
#105000
b111 *
b1 "
b1 ,
b0 #
b0 )
1$
#110000
0$
#115000
b1000 *
1$
#120000
0$
#125000
b1001 *
1$
#130000
0$
#135000
b1010 *
1$
#140000
0$
#145000
b1 +
1$
#150000
0$
#155000
b1011 *
b0 "
b0 ,
b1 #
b1 )
1$
#160000
0$
#165000
b1100 *
1$
#170000
0$
#175000
b0 +
b1101 *
1$
#180000
0$
#185000
b1110 *
b0 #
b0 )
b1 !
b1 -
1$
#190000
0$
#195000
b1111 *
1$
#200000
0$
#205000
b0 *
1$
#210000
0$
#215000
b1 *
1$
